MANIFEST.in
README
setup.cfg
setup.py
LabtoolSuite.egg-info/PKG-INFO
LabtoolSuite.egg-info/SOURCES.txt
LabtoolSuite.egg-info/dependency_links.txt
LabtoolSuite.egg-info/requires.txt
LabtoolSuite.egg-info/top_level.txt
Labtools/HMC5883L.py
Labtools/I2C_class.py
Labtools/MCP4728_class.py
Labtools/MPU6050.py
Labtools/NRF24L01_class.py
Labtools/SPI_class.py
Labtools/__init__.py
Labtools/achan.py
Labtools/calibrate_bipolars.py
Labtools/commands_proto.py
Labtools/custom_widgets.py
Labtools/customui_rc.py
Labtools/digital_channel.py
Labtools/experiment.py
Labtools/experiment_standalone.py
Labtools/interface.py
Labtools/packet_handler.py
Labtools/sensorlist.py
Labtools/template_scope.py
Labtools/Apps/3d_lissajous.py
Labtools/Apps/HMC5883-GY273-magnetometer.py
Labtools/Apps/MPU6050-GY521-accelerometer.py
Labtools/Apps/PyMouse-MPU6050-accel-control.py
Labtools/Apps/__init__.py
Labtools/Apps/accelerometer_cursor.py
Labtools/Apps/bandpass.py
Labtools/Apps/diodeIV.py
Labtools/Apps/transistors.py
Labtools/bin/Experiments
Labtools/bin/Stream
Labtools/bin/oscilloscope
Labtools/calib_data/__init__.py
Labtools/calib_data/calibs2.py
Labtools/docs/Apps.rst
Labtools/docs/I2C_class.py
Labtools/docs/I2C_class.pyc
Labtools/docs/MCP4728_class.py
Labtools/docs/MCP4728_class.pyc
Labtools/docs/NRF24L01_class.py
Labtools/docs/NRF24L01_class.pyc
Labtools/docs/SPI_class.py
Labtools/docs/SPI_class.pyc
Labtools/docs/achan.py
Labtools/docs/achan.pyc
Labtools/docs/auto.sh
Labtools/docs/auto.sh~
Labtools/docs/b.txt
Labtools/docs/commands_proto.py
Labtools/docs/commands_proto.pyc
Labtools/docs/conf.py
Labtools/docs/conf.pyc
Labtools/docs/conf.py~
Labtools/docs/custom.css
Labtools/docs/custom.css~
Labtools/docs/custom_widgets.py
Labtools/docs/custom_widgets.pyc
Labtools/docs/digital_channel.py
Labtools/docs/digital_channel.pyc
Labtools/docs/experiment.py
Labtools/docs/experiment.pyc
Labtools/docs/index.rst
Labtools/docs/index.rst~
Labtools/docs/interface.py
Labtools/docs/interface.pyc
Labtools/docs/packet_handler.py
Labtools/docs/packet_handler.pyc
Labtools/docs/template_exp.py
Labtools/docs/template_exp.pyc
Labtools/docs/Apps/3d_lissajous.py
Labtools/docs/Apps/3d_lissajous.pyc
