Metadata-Version: 1.0
Name: LabtoolSuite
Version: 0.1.6.9
Summary: Package to deal with LabToolSuite
Home-page: https://www.jithinbp.in/
Author: Jithin B.P.
Author-email: jithinbp@gmail.com
License: UNKNOWN
Platform: UNKNOWN
